psym/__init__.py
psym/_utils.py
psym/client.py
psym/config.py
psym/exceptions.py
psym/survey_schema.json
psym/api/__init__.py
psym/api/_flow.py
psym/api/customer.py
psym/api/document_category.py
psym/api/equipment.py
psym/api/equipment_type.py
psym/api/features.py
psym/api/file.py
psym/api/link.py
psym/api/location.py
psym/api/location_template.py
psym/api/location_type.py
psym/api/port.py
psym/api/port_type.py
psym/api/project.py
psym/api/project_type.py
psym/api/property_type.py
psym/api/service.py
psym/api/service_type.py
psym/api/site_survey.py
psym/api/site_survey_schema.py
psym/api/user.py
psym/api/work_order.py
psym/api/work_order_type.py
psym/common/__init__.py
psym/common/cache.py
psym/common/constant.py
psym/common/data_class.py
psym/common/data_enum.py
psym/common/data_format.py
psym/common/endpoint.py
psym/graphql/__init__.py
psym/graphql/enum/__init__.py
psym/graphql/enum/action_type_id.py
psym/graphql/enum/cellular_network_type.py
psym/graphql/enum/check_list_item_enum_selection_mode.py
psym/graphql/enum/check_list_item_type.py
psym/graphql/enum/discovery_method.py
psym/graphql/enum/distance_unit.py
psym/graphql/enum/entry_point_role.py
psym/graphql/enum/equipment_filter_type.py
psym/graphql/enum/exit_point_role.py
psym/graphql/enum/file_type.py
psym/graphql/enum/filter_operator.py
psym/graphql/enum/flow_instance_status.py
psym/graphql/enum/flow_new_instances_policy.py
psym/graphql/enum/image_entity.py
psym/graphql/enum/location_filter_type.py
psym/graphql/enum/project_priority.py
psym/graphql/enum/property_kind.py
psym/graphql/enum/service_status.py
psym/graphql/enum/survey_question_type.py
psym/graphql/enum/survey_status.py
psym/graphql/enum/trigger_type_id.py
psym/graphql/enum/user_role.py
psym/graphql/enum/user_status.py
psym/graphql/enum/variable_expression_type.py
psym/graphql/enum/variable_type.py
psym/graphql/enum/work_order_priority.py
psym/graphql/enum/work_order_status.py
psym/graphql/enum/yes_no_response.py
psym_arriendo_energiav2-2.2.4.dist-info/LICENSE
psym_arriendo_energiav2-2.2.4.dist-info/METADATA
psym_arriendo_energiav2-2.2.4.dist-info/WHEEL
psym_arriendo_energiav2-2.2.4.dist-info/top_level.txt
psym_arriendo_energiav2-2.2.4.dist-info/RECORD
